tokenizer/Abbrev.conf
tokenizer/__init__.py
tokenizer/abbrev.py
tokenizer/definitions.py
tokenizer/main.py
tokenizer/py.typed
tokenizer/tokenizer.py
tokenizer-3.6.2.dist-info/licenses/LICENSE.txt
tokenizer-3.6.2.dist-info/METADATA
tokenizer-3.6.2.dist-info/WHEEL
tokenizer-3.6.2.dist-info/entry_points.txt
tokenizer-3.6.2.dist-info/top_level.txt
tokenizer-3.6.2.dist-info/RECORD
