Metadata-Version: 2.4
Name: tokenizer
Version: 3.6.2
Summary: A fast, compact pure-Python tokenizer for Icelandic text with sentence segmentation
Author-email: "Miðeind ehf." <mideind@mideind.is>
Maintainer-email: Vilhjálmur Þorsteinsson <vt@mideind.is>
License-Expression: MIT
Project-URL: Homepage, https://mideind.is
Project-URL: Repository, https://github.com/mideind/Tokenizer
Project-URL: Documentation, https://github.com/mideind/Tokenizer#readme
Project-URL: Issues, https://github.com/mideind/Tokenizer/issues
Project-URL: Changelog, https://github.com/mideind/Tokenizer#changelog
Keywords: tokenizer,tokenization,icelandic,nlp,natural-language-processing,text-processing,sentence-segmentation,parsing
Classifier: Development Status :: 5 - Production/Stable
Classifier: Intended Audience :: Developers
Classifier: Operating System :: Unix
Classifier: Operating System :: POSIX
Classifier: Operating System :: MacOS
Classifier: Operating System :: Microsoft :: Windows
Classifier: Natural Language :: Icelandic
Classifier: Programming Language :: Python
Classifier: Programming Language :: Python :: 3
Classifier: Programming Language :: Python :: 3.9
Classifier: Programming Language :: Python :: 3.10
Classifier: Programming Language :: Python :: 3.11
Classifier: Programming Language :: Python :: 3.12
Classifier: Programming Language :: Python :: 3.13
Classifier: Programming Language :: Python :: 3.14
Classifier: Programming Language :: Python :: Implementation :: CPython
Classifier: Programming Language :: Python :: Implementation :: PyPy
Classifier: Topic :: Software Development :: Libraries :: Python Modules
Classifier: Topic :: Utilities
Classifier: Topic :: Text Processing :: Linguistic
Requires-Python: >=3.9
License-File: LICENSE.txt
Provides-Extra: test
Requires-Dist: pytest>=7.0; extra == "test"
Provides-Extra: dev
Requires-Dist: pytest>=7.0; extra == "dev"
Requires-Dist: pytest-cov>=4.0; extra == "dev"
Requires-Dist: ruff>=0.1.0; extra == "dev"
Requires-Dist: mypy>=1.0; extra == "dev"
Requires-Dist: build>=1.0; extra == "dev"
Requires-Dist: twine>=4.0; extra == "dev"
Dynamic: license-file
